{"name": "tqqq", "order": 4, "price": 50.26, "currency": "usd", "shares": [[[56.09, 57], [56.56, 16], [56.59, 30], [56.63, 18], [56.67, 2], [56.83, 10]], [[45.48, 37], [48.46, 42], [48.68, 63], [49.46, 12], [50.46, 52], [51.94, 28], [53.14, 40], [53.35, 37], [53.7, 100], [53.84, 9], [54.06, 19], [54.08, 100], [54.14, 58], [54.18, 2], [54.47, 187], [54.58, 164], [54.6, 43], [54.62, 100], [54.66, 200], [54.69, 16], [54.74, 122], [55.5, 37], [55.9, 48], [56.09, 43]], [[57.38, 100]], [], [], []], "surplus": 0, "stages": [{"stage_kind": "custom", "targets": []}, {"stage_kind": "ladder", "defs": [{"id": 22, "sellTimes": 1.02, "profit": 35.0, "minProfit": 20.0, "minShareProfitRatio": 1.02, "disableTrendThreshold": 0.05, "disableDays": [4, 5]}, {"id": 23, "sellTimes": 1.0302, "profit": 45.0, "minProfit": 25.0, "minShareProfitRatio": 1.02, "disableTrendThreshold": 0.1, "disableDays": [4, 5]}, {"id": 24, "sellTimes": 1.040502, "profit": 45.0, "minProfit": 25.0, "minShareProfitRatio": 1.02, "disableTrendThreshold": 0.1, "disableDays": [4, 5]}, {"id": 25, "sellTimes": 1.0510100501000001, "profit": 50.0, "minProfit": 30.0, "minShareProfitRatio": 1.02, "disableTrendThreshold": null, "disableDays": null}, {"id": 26, "sellTimes": 1.0615201506010001, "profit": 50.0, "minProfit": 33.75, "minShareProfitRatio": 1.02, "disableTrendThreshold": null, "disableDays": null}, {"id": 27, "sellTimes": 1.07213535210701, "profit": 50.0, "minProfit": 37.5, "minShareProfitRatio": 1.02, "disableTrendThreshold": null, "disableDays": null}, {"id": 28, "sellTimes": 1.0828567056280802, "profit": 52.5, "minProfit": 45.0, "minShareProfitRatio": 1.02, "disableTrendThreshold": null, "disableDays": null}, {"id": 29, "sellTimes": 1.0936852726843609, "profit": 60.0, "minProfit": 60.0, "minShareProfitRatio": 1.02, "disableTrendThreshold": null, "disableDays": null}, {"id": 30, "sellTimes": 1.1046221254112047, "profit": 75.0, "minProfit": 75.0, "minShareProfitRatio": 1.02, "disableTrendThreshold": null, "disableDays": null}, {"id": 31, "sellTimes": 1.1156683466653166, "profit": 90.0, "minProfit": 90.0, "minShareProfitRatio": 1.02, "disableTrendThreshold": null, "disableDays": null}, {"id": 32, "sellTimes": 1.1268250301319698, "profit": 105.0, "minProfit": 105.0, "minShareProfitRatio": 1.02, "disableTrendThreshold": null, "disableDays": null}, {"id": 33, "sellTimes": 1.1380932804332895, "profit": 112.5, "minProfit": 112.5, "minShareProfitRatio": 1.02, "disableTrendThreshold": null, "disableDays": null}, {"id": 34, "sellTimes": 1.1494742132376226, "profit": 120.0, "minProfit": 120.0, "minShareProfitRatio": 1.02, "disableTrendThreshold": null, "disableDays": null}], "rungs": {"31": [{"definitionID": 31, "target": {"id": "t35", "name": "1.116x", "profit": 90.0, "sell_price": 50.739695999999995, "max_buy_price": 49.74, "min_buy_price": 43.20771, "horizon_request_id": null}, "startPrice": 51.937624956671996, "lowestPrice": 45.4818, "disabled": false}], "32": [{"definitionID": 32, "target": {"id": "t36", "name": "1.127x", "profit": 105.0, "sell_price": 51.249492000000004, "max_buy_price": 50.24, "min_buy_price": 43.20771, "horizon_request_id": null}, "startPrice": 50.459608079999995, "lowestPrice": 45.4818, "disabled": false}], "33": [{"definitionID": 33, "target": {"id": "t37", "name": "1.138x", "profit": 112.5, "sell_price": 51.759288, "max_buy_price": 50.74, "min_buy_price": 43.20771, "horizon_request_id": null}, "startPrice": 50.459608079999995, "lowestPrice": 45.4818, "disabled": false}], "34": [{"definitionID": 34, "target": {"id": "t38", "name": "1.149x", "profit": 120.0, "sell_price": 52.27908, "max_buy_price": 51.25, "min_buy_price": 41.58955265057051, "horizon_request_id": null}, "startPrice": 98.23240735459986, "lowestPrice": 43.778476474284744, "disabled": false}, {"definitionID": 34, "target": {"id": "t39", "name": "1.149x", "profit": 120.0, "sell_price": 52.798872, "max_buy_price": 51.76, "min_buy_price": 41.58955265057051, "horizon_request_id": null}, "startPrice": 98.23240735459986, "lowestPrice": 43.778476474284744, "disabled": false}, {"definitionID": 34, "target": {"id": "t40", "name": "1.149x", "profit": 120.0, "sell_price": 53.32866, "max_buy_price": 52.28, "min_buy_price": 41.58955265057051, "horizon_request_id": null}, "startPrice": 96.32498196907368, "lowestPrice": 43.778476474284744, "disabled": false}, {"definitionID": 34, "target": {"id": "t41", "name": "1.149x", "profit": 120.0, "sell_price": 53.868444000000004, "max_buy_price": 52.81, "min_buy_price": 41.58955265057051, "horizon_request_id": null}, "startPrice": 96.32498196907368, "lowestPrice": 43.778476474284744, "disabled": false}, {"definitionID": 34, "target": {"id": "t42", "name": "1.149x", "profit": 120.0, "sell_price": 54.398232, "max_buy_price": 53.33, "min_buy_price": 41.58955265057051, "horizon_request_id": null}, "startPrice": 95.79291846014135, "lowestPrice": 43.778476474284744, "disabled": false}, {"definitionID": 34, "target": {"id": "t43", "name": "1.149x", "profit": 120.0, "sell_price": 54.948012, "max_buy_price": 53.87, "min_buy_price": 41.58955265057051, "horizon_request_id": null}, "startPrice": 94.11400335041085, "lowestPrice": 43.778476474284744, "disabled": false}, {"definitionID": 34, "target": {"id": "t44", "name": "1.149x", "profit": 120.0, "sell_price": 55.497792000000004, "max_buy_price": 54.41, "min_buy_price": 41.58955265057051, "horizon_request_id": null}, "startPrice": 46.63557049789315, "lowestPrice": 43.778476474284744, "disabled": false}, {"definitionID": 34, "target": {"id": "t45", "name": "1.149x", "profit": 120.0, "sell_price": 56.047572, "max_buy_price": 54.95, "min_buy_price": 41.58955265057051, "horizon_request_id": null}, "startPrice": 45.19323326599954, "lowestPrice": 43.778476474284744, "disabled": false}, {"definitionID": 34, "target": {"id": "t46", "name": "1.149x", "profit": 120.0, "sell_price": 56.607348, "max_buy_price": 55.5, "min_buy_price": 41.58955265057051, "horizon_request_id": null}, "startPrice": 45.19323326599954, "lowestPrice": 43.778476474284744, "disabled": false}, {"definitionID": 34, "target": {"id": "t47", "name": "1.149x", "profit": 120.0, "sell_price": 57.17712, "max_buy_price": 56.06, "min_buy_price": 41.58955265057051, "horizon_request_id": null}, "startPrice": 45.19323326599954, "lowestPrice": 43.778476474284744, "disabled": false}, {"definitionID": 34, "target": {"id": "t48", "name": "1.149x", "profit": 120.0, "sell_price": 57.746892, "max_buy_price": 56.61, "min_buy_price": 41.58955265057051, "horizon_request_id": null}, "startPrice": 44.1633422015312, "lowestPrice": 43.778476474284744, "disabled": false}, {"definitionID": 34, "target": {"id": "t49", "name": "1.149x", "profit": 120.0, "sell_price": 58.326660000000004, "max_buy_price": 57.18, "min_buy_price": 41.58955265057051, "horizon_request_id": null}, "startPrice": 44.1633422015312, "lowestPrice": 43.778476474284744, "disabled": false}, {"definitionID": 34, "target": {"id": "t50", "name": "1.149x", "profit": 120.0, "sell_price": 58.906428, "max_buy_price": 57.75, "min_buy_price": 41.58955265057051, "horizon_request_id": null}, "startPrice": 43.778476474284744, "lowestPrice": 43.778476474284744, "disabled": false}, {"definitionID": 34, "target": {"id": "t51", "name": "1.149x", "profit": 120.0, "sell_price": 59.496192, "max_buy_price": 58.33, "min_buy_price": 43.20771, "horizon_request_id": null}, "startPrice": 57.79153376837901, "lowestPrice": 45.4818, "disabled": false}, {"definitionID": 34, "target": {"id": "t52", "name": "1.149x", "profit": 120.0, "sell_price": 60.095952, "max_buy_price": 58.92, "min_buy_price": 43.20771, "horizon_request_id": null}, "startPrice": 49.760167968, "lowestPrice": 45.4818, "disabled": false}, {"definitionID": 34, "target": {"id": "t53", "name": "1.149x", "profit": 120.0, "sell_price": 60.695712, "max_buy_price": 59.51, "min_buy_price": 43.20771, "horizon_request_id": null}, "startPrice": 49.760167968, "lowestPrice": 45.4818, "disabled": false}, {"definitionID": 34, "target": {"id": "t54", "name": "1.149x", "profit": 120.0, "sell_price": 61.305468, "max_buy_price": 60.1, "min_buy_price": 43.20771, "horizon_request_id": null}, "startPrice": 48.46120776, "lowestPrice": 45.4818, "disabled": false}, {"definitionID": 34, "target": {"id": "t55", "name": "1.149x", "profit": 120.0, "sell_price": 61.915223999999995, "max_buy_price": 60.7, "min_buy_price": 43.20771, "horizon_request_id": null}, "startPrice": 48.46120776, "lowestPrice": 45.4818, "disabled": false}, {"definitionID": 34, "target": {"id": "t56", "name": "1.149x", "profit": 120.0, "sell_price": 62.534976, "max_buy_price": 61.31, "min_buy_price": 43.20771, "horizon_request_id": null}, "startPrice": 45.4818, "lowestPrice": 45.4818, "disabled": false}, {"definitionID": 34, "target": {"id": "t57", "name": "1.149x", "profit": 120.0, "sell_price": 63.164724, "max_buy_price": 61.93, "min_buy_price": 43.20771, "horizon_request_id": null}, "startPrice": 45.4818, "lowestPrice": 45.4818, "disabled": false}, {"definitionID": 34, "target": {"id": "t58", "name": "1.149x", "profit": 120.0, "sell_price": 63.794472, "max_buy_price": 62.54, "min_buy_price": 43.20771, "horizon_request_id": null}, "startPrice": 45.4818, "lowestPrice": 45.4818, "disabled": false}, {"definitionID": 34, "target": {"id": "t59", "name": "1.149x", "profit": 120.0, "sell_price": 64.43421599999999, "max_buy_price": 63.17, "min_buy_price": 43.20771, "horizon_request_id": null}, "startPrice": 45.4818, "lowestPrice": 45.4818, "disabled": false}, {"definitionID": 34, "target": {"id": "t60", "name": "1.149x", "profit": 120.0, "sell_price": 65.07396, "max_buy_price": 63.8, "min_buy_price": 43.20771, "horizon_request_id": null}, "startPrice": 45.4818, "lowestPrice": 45.4818, "disabled": false}, {"definitionID": 34, "target": {"id": "t61", "name": "1.149x", "profit": 120.0, "sell_price": 65.7237, "max_buy_price": 64.43, "min_buy_price": 43.20771, "horizon_request_id": null}, "startPrice": 45.4818, "lowestPrice": 45.4818, "disabled": false}, {"definitionID": 34, "target": {"id": "t62", "name": "1.149x", "profit": 120.0, "sell_price": 66.383436, "max_buy_price": 65.08, "min_buy_price": 43.20771, "horizon_request_id": null}, "startPrice": 45.4818, "lowestPrice": 45.4818, "disabled": false}]}, "rungFrequency": 1.01, "horizon": 66.43037166099704, "minTrendPoint": 49.75, "maxTrendPoint": 50.26, "paused": false}, {"stage_kind": "option", "oTargets": [{"optionID": "o0", "targets": [{"id": "t63", "name": "option-upgrade", "profit": 3650.0, "sell_price": 60.0, "max_buy_price": 57.2, "min_buy_price": 45.5, "horizon_request_id": null}], "profitLevel": 4100.0}]}], "cachedTargets": [{"id": "t64", "name": "1.116x", "profit": 90.0, "sell_price": 50.739695999999995, "max_buy_price": 49.74, "min_buy_price": 43.20771, "horizon_request_id": null}, {"id": "t65", "name": "1.127x", "profit": 105.0, "sell_price": 51.249492000000004, "max_buy_price": 50.24, "min_buy_price": 43.20771, "horizon_request_id": null}, {"id": "t66", "name": "1.138x", "profit": 112.5, "sell_price": 51.759288, "max_buy_price": 50.74, "min_buy_price": 43.20771, "horizon_request_id": null}, {"id": "t67", "name": "1.149x", "profit": 120.0, "sell_price": 52.27908, "max_buy_price": 51.25, "min_buy_price": 41.58955265057051, "horizon_request_id": null}, {"id": "t68", "name": "1.149x", "profit": 120.0, "sell_price": 52.798872, "max_buy_price": 51.76, "min_buy_price": 41.58955265057051, "horizon_request_id": null}, {"id": "t69", "name": "1.149x", "profit": 120.0, "sell_price": 53.32866, "max_buy_price": 52.28, "min_buy_price": 41.58955265057051, "horizon_request_id": null}, {"id": "t70", "name": "1.149x", "profit": 120.0, "sell_price": 53.868444000000004, "max_buy_price": 52.81, "min_buy_price": 41.58955265057051, "horizon_request_id": null}, {"id": "t71", "name": "1.149x", "profit": 120.0, "sell_price": 54.398232, "max_buy_price": 53.33, "min_buy_price": 41.58955265057051, "horizon_request_id": null}, {"id": "t72", "name": "1.149x", "profit": 120.0, "sell_price": 54.948012, "max_buy_price": 53.87, "min_buy_price": 41.58955265057051, "horizon_request_id": null}, {"id": "t73", "name": "1.149x", "profit": 120.0, "sell_price": 55.497792000000004, "max_buy_price": 54.41, "min_buy_price": 41.58955265057051, "horizon_request_id": null}, {"id": "t74", "name": "1.149x", "profit": 120.0, "sell_price": 56.047572, "max_buy_price": 54.95, "min_buy_price": 41.58955265057051, "horizon_request_id": null}, {"id": "t75", "name": "1.149x", "profit": 120.0, "sell_price": 56.607348, "max_buy_price": 55.5, "min_buy_price": 41.58955265057051, "horizon_request_id": null}, {"id": "t76", "name": "1.149x", "profit": 120.0, "sell_price": 57.17712, "max_buy_price": 56.06, "min_buy_price": 41.58955265057051, "horizon_request_id": null}, {"id": "t77", "name": "1.149x", "profit": 120.0, "sell_price": 57.746892, "max_buy_price": 56.61, "min_buy_price": 41.58955265057051, "horizon_request_id": null}, {"id": "t78", "name": "1.149x", "profit": 120.0, "sell_price": 58.326660000000004, "max_buy_price": 57.18, "min_buy_price": 41.58955265057051, "horizon_request_id": null}, {"id": "t79", "name": "1.149x", "profit": 120.0, "sell_price": 58.906428, "max_buy_price": 57.75, "min_buy_price": 41.58955265057051, "horizon_request_id": null}, {"id": "t80", "name": "1.149x", "profit": 120.0, "sell_price": 59.496192, "max_buy_price": 58.33, "min_buy_price": 43.20771, "horizon_request_id": null}, {"id": "t81", "name": "option-upgrade", "profit": 3650.0, "sell_price": 60.0, "max_buy_price": 57.2, "min_buy_price": 45.5, "horizon_request_id": null}, {"id": "t82", "name": "1.149x", "profit": 120.0, "sell_price": 60.095952, "max_buy_price": 58.92, "min_buy_price": 43.20771, "horizon_request_id": null}, {"id": "t83", "name": "1.149x", "profit": 120.0, "sell_price": 60.695712, "max_buy_price": 59.51, "min_buy_price": 43.20771, "horizon_request_id": null}, {"id": "t84", "name": "1.149x", "profit": 120.0, "sell_price": 61.305468, "max_buy_price": 60.1, "min_buy_price": 43.20771, "horizon_request_id": null}, {"id": "t85", "name": "1.149x", "profit": 120.0, "sell_price": 61.915223999999995, "max_buy_price": 60.7, "min_buy_price": 43.20771, "horizon_request_id": null}, {"id": "t86", "name": "1.149x", "profit": 120.0, "sell_price": 62.534976, "max_buy_price": 61.31, "min_buy_price": 43.20771, "horizon_request_id": null}, {"id": "t87", "name": "1.149x", "profit": 120.0, "sell_price": 63.164724, "max_buy_price": 61.93, "min_buy_price": 43.20771, "horizon_request_id": null}, {"id": "t88", "name": "1.149x", "profit": 120.0, "sell_price": 63.794472, "max_buy_price": 62.54, "min_buy_price": 43.20771, "horizon_request_id": null}, {"id": "t89", "name": "1.149x", "profit": 120.0, "sell_price": 64.43421599999999, "max_buy_price": 63.17, "min_buy_price": 43.20771, "horizon_request_id": null}, {"id": "t90", "name": "1.149x", "profit": 120.0, "sell_price": 65.07396, "max_buy_price": 63.8, "min_buy_price": 43.20771, "horizon_request_id": null}, {"id": "t91", "name": "1.149x", "profit": 120.0, "sell_price": 65.7237, "max_buy_price": 64.43, "min_buy_price": 43.20771, "horizon_request_id": null}, {"id": "t92", "name": "1.149x", "profit": 120.0, "sell_price": 66.383436, "max_buy_price": 65.08, "min_buy_price": 43.20771, "horizon_request_id": null}], "borrowEvents": [{"price": 46.5, "nShares": 200, "date": "2025-11-21T00:00:00", "cost": 2400.0, "rebuyAt": 58.21}, {"price": 49.85, "nShares": 500, "date": "2025-12-17T00:00:00", "cost": 0.0, "rebuyAt": 51.61000000000001}, {"price": 47.5, "nShares": 200, "date": "2026-02-05T00:00:00", "cost": 0.0, "rebuyAt": 47.77}], "history": [{"time": "2025-11-20 13:34:49.016537", "description": "Sold [$50.29 x 73]", "physicalShares": 1773}, {"time": "2025-11-20 13:07:37.107155", "description": "Bought 129", "physicalShares": 1902}, {"time": "2025-11-20 14:10:39.049855", "description": "Bought 62", "physicalShares": 1964}, {"time": "2025-11-21 09:48:02.543738", "description": "Bought 200", "physicalShares": 1964}, {"time": "2025-11-21 10:39:37.042146", "description": "Bought 109", "physicalShares": 1873}, {"time": "2025-11-21 12:09:47.246212", "description": "Sold [$45.50 x 13]", "physicalShares": 1860}, {"time": "2025-11-21 14:02:36.728674", "description": "Sold [$45.50 x 13]", "physicalShares": 1847}, {"time": "2025-11-21 14:56:57.679363", "description": "Bought 108", "physicalShares": 1955}, {"time": "2025-11-21 15:55:36.977880", "description": "Bought 20", "physicalShares": 1975}, {"time": "2025-11-23 23:29:52.174169", "description": "Sold [$45.44 x 9]", "physicalShares": 1766}, {"time": "2025-11-24 01:03:14.353735", "description": "Sold [$45.41 x 9]", "physicalShares": 1757}, {"time": "2025-11-24 10:01:00.749406", "description": "Sold [$45.41 x 14]", "physicalShares": 1743}, {"time": "2025-11-24 10:01:12.259427", "description": "Sold [$45.41 x 12]", "physicalShares": 1731}, {"time": "2025-11-24 10:53:23.475326", "description": "Sold [$45.41 x 16]", "physicalShares": 1715}, {"time": "2025-11-24 11:10:00.945158", "description": "Sold [$45.41 x 18]", "physicalShares": 1697}, {"time": "2025-11-24 13:25:53.483958", "description": "Sold [$45.41 x 5, $46.88 x 18]", "physicalShares": 1674}, {"time": "2025-11-25 09:55:38.257325", "description": "Bought 31", "physicalShares": 1705}, {"time": "2025-11-25 11:57:34.016149", "description": "Sold [$48.18 x 13]", "physicalShares": 1692}, {"time": "2025-11-25 12:25:12.140218", "description": "Sold [$48.18 x 14]", "physicalShares": 1678}, {"time": "2025-11-25 12:43:45.820793", "description": "Sold [$46.85 x 24]", "physicalShares": 1654}, {"time": "2025-11-25 15:55:09.680863", "description": "Sold [$46.85 x 20, $47.28 x 3]", "physicalShares": 1631}, {"time": "2025-11-25 21:33:44.427532", "description": "Sold [$47.28 x 17, $48.18 x 7]", "physicalShares": 1607}, {"time": "2025-11-26 09:33:15.196040", "description": "Sold [$48.15 x 24]", "physicalShares": 1583}, {"time": "2025-11-26 11:51:08.612104", "description": "Sold [$48.15 x 22]", "physicalShares": 1561}, {"time": "2025-11-28 00:24:32.885912", "description": "Sold [$48.09 x 2, $49.91 x 11, $50.05 x 13, $51.53 x 7]", "physicalShares": 1528}, {"time": "2025-11-28 10:34:39.425968", "description": "Bought 200", "physicalShares": 1728}, {"time": "2025-11-28 12:59:01.896141", "description": "Sold [$48.09 x 1, $49.91 x 2, $51.53 x 15, $51.61 x 18, $52.03 x 3]", "physicalShares": 1689}, {"time": "2025-11-29 00:19:23.804680", "description": "Sold [$46.29 x 200]", "physicalShares": 1489}, {"time": "2025-11-30 20:35:37.720427", "description": "Bought 21", "physicalShares": 1510}, {"time": "2025-12-01 12:05:06.204681", "description": "Sold [$51.94 x 14]", "physicalShares": 1496}, {"time": "2025-12-01 12:05:06.205682", "description": "Bought 1", "physicalShares": 1497}, {"time": "2025-12-02 09:37:23.529565", "description": "Sold [$47.97 x 1, $51.91 x 15, $52.90 x 6, $52.91 x 24, $53.31 x 2]", "physicalShares": 1449}, {"time": "2025-12-02 10:09:51.644622", "description": "Sold [$49.79 x 1, $53.44 x 21, $53.59 x 33]", "physicalShares": 1394}, {"time": "2025-12-02 11:24:49.157303", "description": "Bought 53", "physicalShares": 1447}, {"time": "2025-12-02 12:21:45.082732", "description": "Sold [$53.59 x 1, $53.65 x 2, $53.91 x 18]", "physicalShares": 1426}, {"time": "2025-12-04 09:13:19.097786", "description": "Sold [$47.91 x 1, $53.85 x 21]", "physicalShares": 1404}, {"time": "2025-12-04 09:14:37.492265", "description": "Sold [$49.73 x 1, $53.85 x 13, $54.09 x 41]", "physicalShares": 1349}, {"time": "2025-12-04 10:12:30.110763", "description": "Bought 24", "physicalShares": 1373}, {"time": "2025-12-04 21:59:57.836043", "description": "Sold [$54.09 x 1, $54.39 x 20]", "physicalShares": 1352}, {"time": "2025-12-05 09:53:59.187900", "description": "Sold [$49.70 x 1, $54.36 x 33, $54.48 x 1, $54.68 x 16]", "physicalShares": 1301}, {"time": "2025-12-05 13:36:14.351379", "description": "Bought 200", "physicalShares": 1501}, {"time": "2025-12-07 20:45:33.461993", "description": "Sold [$53.79 x 200]", "physicalShares": 1301}, {"time": "2025-12-08 12:13:23.039053", "description": "Bought 13", "physicalShares": 1314}, {"time": "2025-12-09 14:31:57.431202", "description": "Bought 100", "physicalShares": 1414}, {"time": "2025-12-10 14:56:55.031804", "description": "Sold [$54.52 x 4, $54.58 x 14]", "physicalShares": 1396}, {"time": "2025-12-10 15:13:08.352342", "description": "Sold [$49.55 x 3, $54.58 x 12, $54.81 x 24, $55.44 x 8]", "physicalShares": 1349}, {"time": "2025-12-10 21:44:16.655330", "description": "Bought 71", "physicalShares": 1420}, {"time": "2025-12-11 15:33:10.450863", "description": "Bought 400", "physicalShares": 1820}, {"time": "2025-12-11 16:12:42.547965", "description": "Sold [$55.17 x 31]", "physicalShares": 1789}, {"time": "2025-12-11 16:42:03.050726", "description": "Sold [$55.17 x 28]", "physicalShares": 1761}, {"time": "2025-12-12 11:06:49.895088", "description": "Bought 117", "physicalShares": 1878}, {"time": "2025-12-15 08:49:14.534407", "description": "Sold [$47.58 x 4, $52.81 x 31]", "physicalShares": 1843}, {"time": "2025-12-15 10:42:48.636460", "description": "Bought 167", "physicalShares": 2010}, {"time": "2025-12-15 22:15:30.356407", "description": "Bought 42", "physicalShares": 2052}, {"time": "2025-12-16 08:32:51.652116", "description": "Sold [$50.77 x 18]", "physicalShares": 2034}, {"time": "2025-12-16 15:37:38.160851", "description": "Sold [$50.77 x 13]", "physicalShares": 2021}, {"time": "2025-12-17 10:01:11.456966", "description": "Bought 15", "physicalShares": 2036}, {"time": "2025-12-17 10:47:40.579069", "description": "Bought 61", "physicalShares": 2097}, {"time": "2025-12-17 15:06:12.483354", "description": "Bought 23", "physicalShares": 2120}, {"time": "2025-12-18 13:49:16.945075", "description": "Sold [$49.77 x 18]", "physicalShares": 2102}, {"time": "2025-12-18 09:30:38.666054", "description": "Sold [$49.77 x 5, $50.71 x 11, $50.72 x 3]", "physicalShares": 2083}, {"time": "2025-12-18 11:02:54.167192", "description": "Sold [$50.72 x 19]", "physicalShares": 2064}, {"time": "2025-12-19 09:32:29.072038", "description": "Sold [$50.69 x 18]", "physicalShares": 2046}, {"time": "2025-12-19 09:45:27.473807", "description": "Sold [$50.69 x 15]", "physicalShares": 2031}, {"time": "2025-12-19 15:40:53.169697", "description": "Bought 400", "physicalShares": 2431}, {"time": "2025-12-19 16:03:24.445667", "description": "Sold [$50.69 x 6, $51.88 x 288, $51.94 x 15, $52.18 x 83]", "physicalShares": 2039}, {"time": "2025-12-19 19:26:02.848660", "description": "Sold [$52.18 x 27]", "physicalShares": 2012}, {"time": "2025-12-22 13:36:51.738235", "description": "Sold [$52.08 x 28]", "physicalShares": 1984}, {"time": "2025-12-22 14:18:39.178473", "description": "Sold [$52.08 x 28]", "physicalShares": 1956}, {"time": "2025-12-23 10:07:38.661425", "description": "Bought 22", "physicalShares": 1978}, {"time": "2025-12-23 15:13:34.622236", "description": "Sold [$52.05 x 1, $52.56 x 13]", "physicalShares": 1964}, {"time": "2025-12-24 11:15:11.509079", "description": "Bought 100", "physicalShares": 2064}, {"time": "2025-12-24 11:18:49.892091", "description": "Bought 100", "physicalShares": 2164}, {"time": "2025-12-24 11:32:17.996895", "description": "Sold [$52.54 x 33]", "physicalShares": 2131}, {"time": "2025-12-29 09:21:36.200254", "description": "Sold [$53.35 x 400]", "physicalShares": 1730}, {"time": "2025-12-29 09:27:06.409449", "description": "Bought 24", "physicalShares": 1754}, {"time": "2025-12-31 19:25:36.605311", "description": "Bought 19", "physicalShares": 1773}, {"time": "2026-01-02 17:55:46.137993", "description": "Bought 51", "physicalShares": 1824}, {"time": "2026-01-05 14:13:45.558454", "description": "Sold [$51.94 x 16]", "physicalShares": 1808}, {"time": "2026-01-06 03:14:50.749041", "description": "Sold [$51.94 x 22]", "physicalShares": 1786}, {"time": "2026-01-06 19:44:43.362923", "description": "Sold [$51.92 x 13, $52.28 x 7]", "physicalShares": 1766}, {"time": "2026-01-06 20:49:50.841570", "description": "Sold [$52.28 x 18]", "physicalShares": 1748}, {"time": "2026-01-07 18:26:53.029833", "description": "Sold [$52.26 x 15, $53.46 x 19, $53.69 x 8]", "physicalShares": 1706}, {"time": "2026-01-08 22:56:28.351434", "description": "Bought 28", "physicalShares": 1734}, {"time": "2026-01-09 19:01:51.163956", "description": "Bought 29", "physicalShares": 1763}, {"time": "2026-01-09 19:35:17.787135", "description": "Sold [$55.05 x 13]", "physicalShares": 1750}, {"time": "2026-01-10 09:19:04.690042", "description": "Sold [$54.48 x 13, $54.69 x 5, $54.87 x 182]", "physicalShares": 1550}, {"time": "2026-01-12 02:44:05.321702", "description": "Bought 20", "physicalShares": 1570}, {"time": "2026-01-14 23:04:04.484216", "description": "Bought 21", "physicalShares": 1591}, {"time": "2026-01-15 08:54:12.227290", "description": "Sold [$53.28 x 19]", "physicalShares": 1572}, {"time": "2026-01-15 17:35:37.752577", "description": "Sold [$53.28 x 2, $53.53 x 14, $53.81 x 4]", "physicalShares": 1552}, {"time": "2026-01-16 21:47:24.074790", "description": "Sold [$53.79 x 20, $54.31 x 12, $54.34 x 15, $54.50 x 1]", "physicalShares": 1504}, {"time": "2026-01-16 22:56:28.565220", "description": "Bought 70", "physicalShares": 1574}, {"time": "2026-01-16 23:05:23.821330", "description": "Bought 76", "physicalShares": 1650}, {"time": "2026-01-16 23:07:48.136355", "description": "Bought 24", "physicalShares": 1674}, {"time": "2026-01-16 23:50:23.180671", "description": "Bought 47", "physicalShares": 1721}, {"time": "2026-01-20 03:29:26.344053", "description": "Bought 38", "physicalShares": 1759}, {"time": "2026-01-20 09:11:08.530631", "description": "Bought 45", "physicalShares": 1804}, {"time": "2026-01-20 23:40:27.828149", "description": "Sold [$50.48 x 1, $51.00 x 17]", "physicalShares": 1786}, {"time": "2026-01-21 01:51:55.701886", "description": "Bought 28", "physicalShares": 1814}, {"time": "2026-01-21 02:52:21.095755", "description": "Bought 25", "physicalShares": 1839}, {"time": "2026-01-21 19:43:36.713704", "description": "Bought 20", "physicalShares": 1859}, {"time": "2026-01-21 22:50:46.572103", "description": "Sold [$50.60 x 20, $50.98 x 3]", "physicalShares": 1836}, {"time": "2026-01-21 23:30:53.653970", "description": "Sold [$50.98 x 25, $51.08 x 2]", "physicalShares": 1809}, {"time": "2026-01-21 23:34:46.235543", "description": "Sold [$51.08 x 16]", "physicalShares": 1793}, {"time": "2026-01-22 01:11:14.654567", "description": "Bought 65", "physicalShares": 1858}, {"time": "2026-01-22 10:09:54.385903", "description": "Sold [$51.08 x 7, $51.10 x 65, $51.58 x 10]", "physicalShares": 1776}, {"time": "2026-01-22 16:07:59.513000", "description": "Sold [$51.56 x 16]", "physicalShares": 1760}, {"time": "2026-01-22 16:56:34.131336", "description": "Sold [$51.56 x 2, $52.44 x 22]", "physicalShares": 1736}, {"time": "2026-01-23 03:44:55.439938", "description": "Bought 100", "physicalShares": 1599}, {"time": "2026-01-23 03:50:02.268984", "description": "Bought 200", "physicalShares": 1799}, {"time": "2026-01-23 19:26:26.799488", "description": "Bought 30", "physicalShares": 1829}, {"time": "2026-01-23 23:22:56.307162", "description": "Sold [$52.42 x 16, $53.30 x 4]", "physicalShares": 1809}, {"time": "2026-01-23 23:35:02.275409", "description": "Sold [$53.30 x 26, $53.63 x 10]", "physicalShares": 1773}, {"time": "2026-01-24 00:48:15.859459", "description": "Bought 43", "physicalShares": 1816}, {"time": "2026-01-26 03:46:36.589035", "description": "Bought 61", "physicalShares": 1877}, {"time": "2026-01-26 22:36:07.277632", "description": "Sold [$53.73 x 33]", "physicalShares": 1844}, {"time": "2026-01-27 00:14:26.163538", "description": "Sold [$53.73 x 28, $54.40 x 3]", "physicalShares": 1813}, {"time": "2026-01-27 04:06:15.998251", "description": "Sold [$54.40 x 55]", "physicalShares": 1592}, {"time": "2026-01-27 19:58:33.295093", "description": "Sold [$54.38 x 9, $54.49 x 18, $54.67 x 48]", "physicalShares": 1517}, {"time": "2026-01-27 23:49:16.913139", "description": "Sold [$54.38 x 1, $54.67 x 56]", "physicalShares": 1460}, {"time": "2026-01-29 00:54:49.305899", "description": "Bought 16", "physicalShares": 1476}, {"time": "2026-01-29 17:12:03.979521", "description": "Sold [$54.63 x 13]", "physicalShares": 1463}, {"time": "2026-01-29 22:33:26.976457", "description": "Bought 18", "physicalShares": 1481}, {"time": "2026-01-29 22:45:29.856874", "description": "Bought 37", "physicalShares": 1518}, {"time": "2026-01-29 23:00:59.845953", "description": "Bought 16", "physicalShares": 1534}, {"time": "2026-01-29 23:36:07.953493", "description": "Bought 21", "physicalShares": 1555}, {"time": "2026-01-29 23:55:13.887219", "description": "Bought 34", "physicalShares": 1589}, {"time": "2026-01-30 01:32:02.109215", "description": "Sold [$53.10 x 23, $54.63 x 83]", "physicalShares": 1483}, {"time": "2026-01-30 01:39:44.401130", "description": "Sold [$53.10 x 5]", "physicalShares": 1478}, {"time": "2026-01-31 03:59:02.641272", "description": "Bought 200", "physicalShares": 1678}, {"time": "2026-01-30 20:18:54.671695", "description": "Sold [$52.25 x 200]", "physicalShares": 1478}, {"time": "2026-02-02 23:21:46.643437", "description": "Sold [$53.02 x 6, $53.92 x 12]", "physicalShares": 1460}, {"time": "2026-02-03 22:55:37.748224", "description": "Bought 58", "physicalShares": 1518}, {"time": "2026-02-03 23:23:21.003250", "description": "Bought 40", "physicalShares": 1558}, {"time": "2026-02-04 01:36:54.305684", "description": "Bought 28", "physicalShares": 1586}, {"time": "2026-02-04 23:02:03.401357", "description": "Bought 52", "physicalShares": 1638}, {"time": "2026-02-05 00:46:51.464218", "description": "Bought 12", "physicalShares": 1650}, {"time": "2026-02-05 01:50:20.238751", "description": "Bought 48", "physicalShares": 1698}, {"time": "2026-02-04 19:51:04.679520", "description": "Sold [$48.50 x 6]", "physicalShares": 1692}, {"time": "2026-02-05 20:35:52.924881", "description": "Bought 63", "physicalShares": 1755}, {"time": "2026-02-06 00:08:54.721619", "description": "Bought 137", "physicalShares": 1892}, {"time": "2026-02-06 00:10:11.887811", "description": "Bought 37", "physicalShares": 1929}, {"time": "2026-02-06 02:12:33.179620", "description": "Sold [$45.50 x 56]", "physicalShares": 1873}, {"time": "2026-02-06 12:01:17.451783", "description": "Sold [$45.48 x 38]", "physicalShares": 1835}, {"time": "2026-02-06 14:51:49.436990", "description": "Sold [$45.48 x 12]", "physicalShares": 1823}, {"time": "2026-02-06 16:24:29.443980", "description": "Sold [$45.48 x 15]", "physicalShares": 1808}, {"time": "2026-02-06 20:31:08.197254", "description": "Sold [$45.48 x 16]", "physicalShares": 1792}], "options": [{"mode": "PUT", "date": "2027-01-15", "strikePrice": 50, "nContracts": 10, "price": 8.98, "buyCost": 7613.0, "theta": -0.025, "id": "o0", "upgradeFunding": 525.5937500000002, "upgradeTargets": [{"assetSellPrice": 60.0, "optionSellPrice": 4.0}]}], "writeOptions": [{"mode": "CALL", "date": "2025-07-25", "strikePrice": 86, "nContracts": 1, "price": 2.35, "id": "o1"}, {"mode": "CALL", "date": "2025-08-01", "strikePrice": 90, "nContracts": 1, "price": 1.64, "id": "o2"}, {"mode": "CALL", "date": "2025-08-08", "strikePrice": 84, "nContracts": 1, "price": 2.54, "id": "o3"}, {"mode": "CALL", "date": "2025-08-15", "strikePrice": 92, "nContracts": 1, "price": 1.84, "id": "o4"}, {"mode": "CALL", "date": "2025-08-22", "strikePrice": 96, "nContracts": 1, "price": 2.0, "id": "o5"}, {"mode": "CALL", "date": "2025-08-29", "strikePrice": 88, "nContracts": 1, "price": 2.32, "id": "o6"}, {"mode": "CALL", "date": "2025-09-05", "strikePrice": 92, "nContracts": 1, "price": 2.16, "id": "o7"}, {"mode": "CALL", "date": "2025-09-12", "strikePrice": 94, "nContracts": 1, "price": 1.7, "id": "o8"}, {"mode": "CALL", "date": "2025-09-19", "strikePrice": 97, "nContracts": 1, "price": 1.93, "id": "o9"}, {"mode": "CALL", "date": "2025-09-26", "strikePrice": 103, "nContracts": 4, "price": 1.92, "id": "o10"}, {"mode": "CALL", "date": "2025-10-03", "strikePrice": 102, "nContracts": 1, "price": 2.1, "id": "o11"}, {"mode": "CALL", "date": "2025-10-03", "strikePrice": 105, "nContracts": 1, "price": 100.0, "id": "o12"}, {"mode": "CALL", "date": "2025-10-17", "strikePrice": 103, "nContracts": 1, "price": 2.9, "id": "o13"}, {"mode": "CALL", "date": "2025-10-24", "strikePrice": 104, "nContracts": 1, "price": 3.4, "id": "o14"}, {"mode": "CALL", "date": "2025-10-31", "strikePrice": 107, "nContracts": 1, "price": 3.35, "id": "o15"}, {"mode": "CALL", "date": "2025-11-07", "strikePrice": 118, "nContracts": 1, "price": 4.1, "id": "o16"}, {"mode": "CALL", "date": "2025-11-07", "strikePrice": 116, "nContracts": 1, "price": 3.55, "id": "o17"}, {"mode": "CALL", "date": "2025-11-21", "strikePrice": 107, "nContracts": 1, "price": 3.9, "id": "o18"}, {"mode": "CALL", "date": "2025-11-28", "strikePrice": 47, "nContracts": 2, "price": 2.25, "id": "o19"}, {"mode": "CALL", "date": "2025-12-05", "strikePrice": 54.5, "nContracts": 2, "price": 1.25, "id": "o20"}, {"mode": "CALL", "date": "2025-12-12", "strikePrice": 56.5, "nContracts": 2, "price": 1.52, "id": "o21"}], "weeklyCallGoalNContracts": 1, "dailyDecayFactor": 0.0004, "baseChange": 0.0, "profitDestOverrides": [], "marginRequirement": 0.4, "borrowRaiseFund": 2.399999999999989}